agentops/__init__.py
agentops/analyze_run.py
agentops/annotate.py
agentops/arg_configs.py
agentops/batch_annotate.py
agentops/clients.py
agentops/data_annotator.py
agentops/description_quality_checker.py
agentops/evaluation.py
agentops/evaluation_package.py
agentops/langfuse_evaluation_package.py
agentops/llm_matching.py
agentops/llm_rag_eval.py
agentops/llm_safety_eval.py
agentops/main.py
agentops/quick_eval.py
agentops/record_chat.py
agentops/resource_map.py
agentops/runner.py
agentops/scheduler.py
agentops/service_instance.py
agentops/simulation_runner.py
agentops/test_prompt.py
agentops/tool_planner.py
agentops/type.py
agentops/wxo_client.py
agentops/automatic_eval_generation/__init__.py
agentops/automatic_eval_generation/data_generator.py
agentops/automatic_eval_generation/tool_seq_generator.py
agentops/automatic_eval_generation/workflow_converter.py
agentops/collection/__init__.py
agentops/collection/arize_collection.py
agentops/collection/collection.py
agentops/collection/collection_base.py
agentops/collection/langfuse_collection.py
agentops/compare_runs/__init__.py
agentops/compare_runs/compare_2_runs.py
agentops/compare_runs/diff.py
agentops/compare_runs/model.py
agentops/evaluation_controller/evaluation_controller.py
agentops/external_agent/__init__.py
agentops/external_agent/external_validate.py
agentops/external_agent/performance_test.py
agentops/external_agent/types.py
agentops/extractors/__init__.py
agentops/extractors/dummy_extractor.py
agentops/extractors/expected_tool_extractor.py
agentops/extractors/extractor_base.py
agentops/extractors/labeled_messages.py
agentops/extractors/orchestrate_routing_tool_call_extractor.py
agentops/extractors/utils.py
agentops/llm_user/base_user.py
agentops/llm_user/demo_usage_llm_user.py
agentops/llm_user/llm_user_v1.py
agentops/llm_user/llm_user_v2.py
agentops/metrics/__init__.py
agentops/metrics/conversation_quality.py
agentops/metrics/dummy_metric.py
agentops/metrics/evaluations.py
ibm_watsonx_orchestrate_evaluation_framework-1.2.1.dist-info/METADATA
ibm_watsonx_orchestrate_evaluation_framework-1.2.1.dist-info/WHEEL
ibm_watsonx_orchestrate_evaluation_framework-1.2.1.dist-info/top_level.txt
ibm_watsonx_orchestrate_evaluation_framework-1.2.1.dist-info/RECORD
